pyxrdspec/__init__.py
pyxrdspec/pyxrdspec.py
pyxrdspec-0.0.1.dist-info/METADATA
pyxrdspec-0.0.1.dist-info/WHEEL
pyxrdspec-0.0.1.dist-info/top_level.txt
pyxrdspec-0.0.1.dist-info/RECORD
