Metadata-Version: 2.1
Name: pyxrdspec
Version: 0.0.1
Summary: Tool for plotting XRD from the CRYSTAL software
Home-page: UNKNOWN
Author: Alessandro Cossard
Author-email: <alessandro.cossard@unito.it>
License: UNKNOWN
Keywords: python,quantum,xrd,chemistry,physics,spectrum
Platform: UNKNOWN
Classifier: Development Status :: 1 - Planning
Classifier: Intended Audience :: Developers
Classifier: Programming Language :: Python :: 3
Classifier: Operating System :: Unix
Classifier: Operating System :: MacOS :: MacOS X
Classifier: Operating System :: Microsoft :: Windows
